asmd/AudioScoreDataset.m
asmd/__init__.py
asmd/_alignment_stats.pkl
asmd/alignment_stats.py
asmd/asmd.pyx
asmd/audioscoredataset.py
asmd/conversion_tool.pyx
asmd/convert_from_file.pyx
asmd/datasets.json
asmd/definitions/Bach10.json
asmd/definitions/Maestro.json
asmd/definitions/MusicNet.json
asmd/definitions/PHENICX.json
asmd/definitions/SMD.json
asmd/definitions/TRIOS_dataset.json
asmd/definitions/traditional_flute.json
asmd/definitions/vienna_corpus.json
asmd/generate_ground_truth.py
asmd/idiot.py
asmd/install.py
asmd/my_scores/Chopin_op10_no3.mid
asmd/my_scores/Chopin_op38.mid
asmd/my_scores/Mozart_K331_1st-mov.mid
asmd/my_scores/Schubert_D783_no15.mid
asmd/utils.pyx
asmd/conversion_tool.cpython-36m-x86_64-linux-gnu.so
asmd/audioscoredataset.cpython-36m-x86_64-linux-gnu.so
asmd/utils.cpython-36m-x86_64-linux-gnu.so
asmd/convert_from_file.cpython-36m-x86_64-linux-gnu.so
asmd-0.2.dist-info/LICENSE
asmd-0.2.dist-info/WHEEL
asmd-0.2.dist-info/METADATA
asmd-0.2.dist-info/RECORD
