Metadata-Version: 2.1
Name: asmd
Version: 0.2
Summary: Audio-Score Meta-Dataset
Home-page: https://asmd.readthedocs.org
License: MIT
Author: Federico Simonetta
Author-email: federico.simonetta@unimi.it
Requires-Python: >=3.6.9,<4.0.0
Classifier: Intended Audience :: Developers
Classifier: Intended Audience :: Other Audience
Classifier: Intended Audience :: Science/Research
Classifier: License :: OSI Approved :: MIT License
Classifier: Programming Language :: Python :: 3
Classifier: Programming Language :: Python :: 3.7
Classifier: Programming Language :: Python :: 3.8
Classifier: Programming Language :: Python :: 3.9
Classifier: Topic :: Multimedia :: Sound/Audio
Requires-Dist: alive-progress (>=1.3.3,<2.0.0)
Requires-Dist: beautifulsoup4 (>=4.8.2,<5.0.0)
Requires-Dist: decorator (>=4.4.1,<5.0.0)
Requires-Dist: essentia (>=2.1b6.dev184,<3.0)
Requires-Dist: joblib (>=0.14.1,<0.15.0)
Requires-Dist: mega.py (>=1.0.6,<2.0.0)
Requires-Dist: numpy (>=1.18.1,<2.0.0)
Requires-Dist: plotly (>=4.4.1,<5.0.0)
Requires-Dist: pretty_midi (>=0.2.8,<0.3.0)
Requires-Dist: prompt_toolkit (>=3.0.3,<4.0.0)
Requires-Dist: pyfiglet (>=0.8.post1,<0.9)
Requires-Dist: requests (>=2.22.0,<3.0.0)
Requires-Dist: scikit_learn (>=0.22.1,<0.23.0)
Requires-Dist: setuptools (>=45.2.0,<46.0.0)
Requires-Dist: tqdm (>=4.43.0,<5.0.0)
Project-URL: Documentation, https://asmd.readthedocs.org
Project-URL: Repository, https://gitlab.di.unimi.it/federicosimonetta/asmd/
